{"data_mtime": 1675934283, "dep_lines": [1, 2, 3, 4, 1, 1], "dep_prios": [10, 5, 5, 5, 5, 30], "dependencies": ["sys", "_typeshed", "typing", "typing_extensions", "builtins", "abc"], "hash": "4bb74d17badc6d69c1b42b136e05e45639359f375bc727eb91396b4785621e77", "id": "termios", "ignore_all": true, "interface_hash": "c731674d2c1c5db2199d7f0ef84f3369801b9986b40ce1912b802def03781c9e", "mtime": 1674341296, "options": {"allow_redefinition": false, "allow_untyped_globals": false, "always_false": [], "always_true": [], "bazel": false, "check_untyped_defs": true, "disable_bytearray_promotion": false, "disable_error_code": ["arg-type", "attr-defined", "import", "misc", "no-any-return", "no-redef", "no-untyped-call", "no-untyped-def", "operator", "type-arg", "var-annotated", "union-attr"], "disable_memoryview_promotion": false, "disabled_error_codes": ["arg-type", "attr-defined", "import", "misc", "no-any-return", "no-redef", "no-untyped-call", "no-untyped-def", "operator", "type-arg", "union-attr", "var-annotated"], "disallow_any_decorated": false, "disallow_any_explicit": false, "disallow_any_expr": false, "disallow_any_generics": true, "disallow_any_unimported": false, "disallow_incomplete_defs": true, "disallow_subclassing_any": true, "disallow_untyped_calls": true, "disallow_untyped_decorators": true, "disallow_untyped_defs": true, "enable_error_code": [], "enabled_error_codes": [], "follow_imports": "normal", "follow_imports_for_stubs": false, "ignore_errors": false, "ignore_missing_imports": false, "implicit_optional": false, "implicit_reexport": false, "local_partial_types": false, "mypyc": false, "platform": "darwin", "plugins": [], "strict_concatenate": true, "strict_equality": true, "strict_optional": true, "warn_no_return": true, "warn_return_any": true, "warn_unreachable": false, "warn_unused_ignores": true}, "path": "/Users/stanislaw/workspace/projects/code/strictdoc/.venv-default/lib/python3.7/site-packages/mypy/typeshed/stdlib/termios.pyi", "plugin_data": null, "size": 4753, "suppressed": [], "version_id": "0.991"}